intersdk/__init__.py
intersdk/inter.py
intersdk/py.typed
intersdk/autenticacao/__init__.py
intersdk/autenticacao/autenticacao.py
intersdk/autenticacao/token.py
intersdk/cobranca/__init__.py
intersdk/cobranca/cobranca.py
intersdk/cobranca/components/__init__.py
intersdk/cobranca/components/boleto.py
intersdk/cobranca/components/componente_financeiro.py
intersdk/cobranca/components/endereco.py
intersdk/cobranca/components/pessoa.py
intersdk/misc/__init__.py
intersdk/misc/exceptions.py
intersdk/misc/typing.py
intersdk/misc/validators/__init__.py
intersdk/misc/validators/boleto_validator.py
intersdk/misc/validators/componente_financeiro_validator.py
intersdk/misc/validators/endereco_validator.py
intersdk/misc/validators/path_validator.py
intersdk/misc/validators/pessoa_validator.py
intersdk-0.0.3.dist-info/METADATA
intersdk-0.0.3.dist-info/WHEEL
intersdk-0.0.3.dist-info/top_level.txt
intersdk-0.0.3.dist-info/RECORD
